staffology/__init__.py
staffology/client.py
staffology/enum_override.py
staffology/propagate_exceptions.py
staffology/py.typed
staffology/types.py
staffology/api/__init__.py
staffology/api/account/__init__.py
staffology/api/account/activate_account.py
staffology/api/account/change_email_address_account.py
staffology/api/account/create_api_key_account.py
staffology/api/account/create_demo_employer_account.py
staffology/api/account/delete_api_key_account.py
staffology/api/account/get_account.py
staffology/api/account/get_api_key_account.py
staffology/api/account/get_employer_defaults_account.py
staffology/api/account/get_invitations_account.py
staffology/api/account/get_tenant_account.py
staffology/api/account/list_api_keys_account.py
staffology/api/account/profile_account.py
staffology/api/account/set_employer_defaults_account.py
staffology/api/account/update_photo_account.py
staffology/api/account/verify_account.py
staffology/api/account/verify_response_account.py
staffology/api/analysis_category/__init__.py
staffology/api/analysis_category/create_analysis_category.py
staffology/api/analysis_category/create_analysis_category_code_analysis_category.py
staffology/api/analysis_category/delete_analysis_category.py
staffology/api/analysis_category/delete_analysis_category_code_analysis_category.py
staffology/api/analysis_category/get_analysis_category.py
staffology/api/analysis_category/get_analysis_category_code_analysis_category.py
staffology/api/analysis_category/get_codes_analysis_category.py
staffology/api/analysis_category/index_analysis_category.py
staffology/api/analysis_category/update_analysis_category.py
staffology/api/analysis_category/update_analysis_category_code_analysis_category.py
staffology/api/async_report/__init__.py
staffology/api/async_report/queue_gross_to_net_request_async_report.py
staffology/api/attachment_order/__init__.py
staffology/api/attachment_order/add_document_attachment_order.py
staffology-0.1.7.dist-info/METADATA
staffology-0.1.7.dist-info/WHEEL
staffology-0.1.7.dist-info/top_level.txt
staffology-0.1.7.dist-info/RECORD
